{
  "main": {
    "id": "9cfba0c725f64c56",
    "type": "split",
    "children": [
      {
        "id": "317b32484ad8d2e5",
        "type": "tabs",
        "children": [
          {
            "id": "9495ab74881365b3",
            "type": "leaf",
            "state": {
              "type": "markdown",
              "state": {
                "file": "Wiki/Mathematics.md",
                "mode": "source",
                "source": false,
                "backlinks": true,
                "backlinkOpts": {
                  "collapseAll": false,
                  "extraContext": false,
                  "sortOrder": "alphabetical",
                  "showSearch": false,
                  "searchQuery": "",
                  "backlinkCollapsed": false,
                  "unlinkedCollapsed": true
                }
              },
              "icon": "lucide-file",
              "title": "Mathematics"
            }
          },
          {
            "id": "4bd31547a9942141",
            "type": "leaf",
            "state": {
              "type": "markdown",
              "state": {
                "file": "Wiki/This Wiki.md",
                "mode": "source",
                "source": false,
                "backlinks": true,
                "backlinkOpts": {
                  "collapseAll": false,
                  "extraContext": false,
                  "sortOrder": "alphabetical",
                  "showSearch": false,
                  "searchQuery": "",
                  "backlinkCollapsed": false,
                  "unlinkedCollapsed": true
                }
              },
              "icon": "lucide-file",
              "title": "This Wiki"
            }
          },
          {
            "id": "859d0e8053b75447",
            "type": "leaf",
            "state": {
              "type": "markdown",
              "state": {
                "file": "Wiki/Research in mathematics.md",
                "mode": "source",
                "source": false,
                "backlinks": true,
                "backlinkOpts": {
                  "collapseAll": false,
                  "extraContext": false,
                  "sortOrder": "alphabetical",
                  "showSearch": false,
                  "searchQuery": "",
                  "backlinkCollapsed": false,
                  "unlinkedCollapsed": true
                }
              },
              "icon": "lucide-file",
              "title": "Research in mathematics"
            }
          }
        ],
        "currentTab": 2
      }
    ],
    "direction": "vertical"
  },
  "left": {
    "id": "e2bb1f4ceacd18c5",
    "type": "split",
    "children": [
      {
        "id": "0927e30b1f1da7e2",
        "type": "tabs",
        "children": [
          {
            "id": "84a7dbc0eef00c67",
            "type": "leaf",
            "state": {
              "type": "file-explorer",
              "state": {
                "sortOrder": "alphabetical",
                "autoReveal": true
              },
              "icon": "lucide-folder-closed",
              "title": "Files"
            }
          },
          {
            "id": "25982a236ba020bc",
            "type": "leaf",
            "state": {
              "type": "search",
              "state": {
                "query": "",
                "matchingCase": false,
                "explainSearch": false,
                "collapseAll": false,
                "extraContext": false,
                "sortOrder": "alphabetical"
              },
              "icon": "lucide-search",
              "title": "Search"
            }
          },
          {
            "id": "6aa646695f365bfa",
            "type": "leaf",
            "state": {
              "type": "bookmarks",
              "state": {},
              "icon": "lucide-bookmark",
              "title": "Bookmarks"
            }
          }
        ]
      }
    ],
    "direction": "horizontal",
    "width": 300
  },
  "right": {
    "id": "39d9995e016ba0fc",
    "type": "split",
    "children": [
      {
        "id": "f037a5c2e20827d2",
        "type": "tabs",
        "children": [
          {
            "id": "79678041708794f3",
            "type": "leaf",
            "state": {
              "type": "backlink",
              "state": {
                "file": "Wiki/Research in mathematics.md",
                "collapseAll": false,
                "extraContext": false,
                "sortOrder": "alphabetical",
                "showSearch": false,
                "searchQuery": "",
                "backlinkCollapsed": false,
                "unlinkedCollapsed": true
              },
              "icon": "links-coming-in",
              "title": "Backlinks for Research in mathematics"
            }
          },
          {
            "id": "b5aca63b4f3d004e",
            "type": "leaf",
            "state": {
              "type": "outgoing-link",
              "state": {
                "linksCollapsed": false,
                "unlinkedCollapsed": true
              },
              "icon": "links-going-out",
              "title": "Outgoing links"
            }
          },
          {
            "id": "4d598401d609464a",
            "type": "leaf",
            "state": {
              "type": "tag",
              "state": {
                "sortOrder": "frequency",
                "useHierarchy": true,
                "showSearch": false,
                "searchQuery": ""
              },
              "icon": "lucide-tags",
              "title": "Tags"
            }
          },
          {
            "id": "208d335a8d01cea1",
            "type": "leaf",
            "state": {
              "type": "all-properties",
              "state": {
                "sortOrder": "frequency",
                "showSearch": false,
                "searchQuery": ""
              },
              "icon": "lucide-archive",
              "title": "All properties"
            }
          },
          {
            "id": "fae926a08516261d",
            "type": "leaf",
            "state": {
              "type": "outline",
              "state": {
                "followCursor": false,
                "showSearch": false,
                "searchQuery": ""
              },
              "icon": "lucide-list",
              "title": "Outline"
            }
          },
          {
            "id": "54e8edcd3eb2bbac",
            "type": "leaf",
            "state": {
              "type": "footnotes",
              "state": {},
              "icon": "lucide-file-signature",
              "title": "Footnotes"
            }
          },
          {
            "id": "38fa337f07f239ba",
            "type": "leaf",
            "state": {
              "type": "calendar",
              "state": {},
              "icon": "calendar-with-checkmark",
              "title": "Calendar"
            }
          }
        ]
      }
    ],
    "direction": "horizontal",
    "width": 300,
    "collapsed": true
  },
  "left-ribbon": {
    "hiddenItems": {
      "obsidian-kanban:Create new board": false,
      "switcher:Open quick switcher": false,
      "graph:Open graph view": false,
      "canvas:Create new canvas": false,
      "daily-notes:Open today's daily note": false,
      "templates:Insert template": false,
      "command-palette:Open command palette": false,
      "bases:Create new base": false,
      "publish:Publish changes...": false,
      "table-editor-obsidian:Advanced Tables Toolbar": false,
      "obsidian-git:Open Git source control": false
    }
  },
  "active": "859d0e8053b75447",
  "lastOpenFiles": [
    "Wiki/Research in Mathematics (Legacy).md",
    "Wiki/Research in mathematics.md",
    "Research in mathematics.md",
    "Wiki/Research.md",
    "Analysis.md",
    "Untitled.md",
    "Wiki/This Wiki.md",
    "Wiki/Mathematics.md",
    "Welcome.md",
    "Wiki"
  ]
}